odoo/addons/stock_kardex/LICENSE
odoo/addons/stock_kardex/README.rst
odoo/addons/stock_kardex/__init__.py
odoo/addons/stock_kardex/__manifest__.py
odoo/addons/stock_kardex/demo/document_demo.xml
odoo/addons/stock_kardex/images/screen.png
odoo/addons/stock_kardex/models/__init__.py
odoo/addons/stock_kardex/models/config.py
odoo/addons/stock_kardex/models/helper.py
odoo/addons/stock_kardex/models/kardex_transfer_mixin.py
odoo/addons/stock_kardex/models/mrp_bom.py
odoo/addons/stock_kardex/models/mrp_production.py
odoo/addons/stock_kardex/models/purchase_order.py
odoo/addons/stock_kardex/models/res_config_settings.py
odoo/addons/stock_kardex/models/sale_order.py
odoo/addons/stock_kardex/models/stock_lot_delete_wizard.py
odoo/addons/stock_kardex/models/stock_move.py
odoo/addons/stock_kardex/models/stock_move_line.py
odoo/addons/stock_kardex/models/stock_picking.py
odoo/addons/stock_kardex/models/stock_picking_journal.py
odoo/addons/stock_kardex/models/stock_picking_type.py
odoo/addons/stock_kardex/models/stock_quant.py
odoo/addons/stock_kardex/models/stock_quant_delete_wizard.py
odoo/addons/stock_kardex/models/sync_report.py
odoo/addons/stock_kardex/models/transfer.py
odoo/addons/stock_kardex/models/validation_mixin.py
odoo/addons/stock_kardex/security/ir.model.access.csv
odoo/addons/stock_kardex/static/description/icon.png
odoo/addons/stock_kardex/static/description/index.html
odoo/addons/stock_kardex/static/src/css/style.css
odoo/addons/stock_kardex/static/src/js/sync_pickings.js
odoo/addons/stock_kardex/static/src/js/widget.js
odoo/addons/stock_kardex/static/src/xml/sync_pickings.xml
odoo/addons/stock_kardex/tests/__init__.py
odoo/addons/stock_kardex/tests/test_purchase_order_validation.py
odoo/addons/stock_kardex/views/kardex_bom_views.xml
odoo/addons/stock_kardex/views/kardex_move_line_views.xml
odoo/addons/stock_kardex/views/kardex_picking_type_views.xml
odoo/addons/stock_kardex/views/kardex_production_views.xml
odoo_addon_stock_kardex-18.0.1.0.0.dist-info/METADATA
odoo_addon_stock_kardex-18.0.1.0.0.dist-info/WHEEL
odoo_addon_stock_kardex-18.0.1.0.0.dist-info/top_level.txt
odoo_addon_stock_kardex-18.0.1.0.0.dist-info/RECORD
